janus/__init__.py
janus/circuit/__init__.py
janus/circuit/annotated_operation.py
janus/circuit/circuit.py
janus/circuit/clbit.py
janus/circuit/converters.py
janus/circuit/dag.py
janus/circuit/gate.py
janus/circuit/instruction.py
janus/circuit/layer.py
janus/circuit/operation.py
janus/circuit/parameter.py
janus/circuit/qubit.py
janus/circuit/test_circuit.py
janus/circuit/library/__init__.py
janus/circuit/library/p.py
janus/circuit/library/qft.py
janus/circuit/library/rz.py
janus/circuit/library/standard_gates.py
janus/circuit/library/u1.py
janus/compat/__init__.py
janus/compat/_optionals.py
janus/compat/clifford.py
janus/compat/clifford_circuits.py
janus/compat/commutation_cancellation.py
janus/compat/commutation_checker.py
janus/compat/control_flow_utils.py
janus/compat/converters_dag_to_dagdependency.py
janus/compat/converters_dagdependency_to_dag.py
janus/compat/dagdependency.py
janus/compat/dagdepnode.py
janus/compat/exceptions.py
janus/compat/operator.py
janus/compat/passmanager.py
janus/compat/quaternion.py
janus/compat/accelerate/__init__.py
janus/compat/accelerate/euler_one_qubit_decomposer.py
janus/compat/accelerate/two_qubit_decompose.py
janus/compat/accelerate/synthesis/__init__.py
janus/compat/accelerate/synthesis/linear.py
janus/compat/accelerate/synthesis/clifford/__init__.py
janus/compat/accelerate/synthesis/clifford/bm.py
janus/compat/accelerate/synthesis/clifford/greedy.py
janus/compat/converters/__init__.py
janus/compat/converters/circuit_to_dag.py
janus/compat/converters/circuit_to_dagdependency.py
janus/compat/converters/circuit_to_dagdependency_v2.py
janus/compat/converters/circuit_to_gate.py
janus/compat/converters/circuit_to_instruction.py
janus/compat/converters/dag_to_circuit.py
janus/compat/converters/dag_to_dagdependency.py
janus/compat/converters/dag_to_dagdependency_v2.py
janus/compat/converters/dagdependency_to_circuit.py
janus/compat/converters/dagdependency_to_dag.py
janus/compat/synthesis/__init__.py
janus_quantum-1.0.2.dist-info/LICENSE
janus_quantum-1.0.2.dist-info/METADATA
janus_quantum-1.0.2.dist-info/WHEEL
janus_quantum-1.0.2.dist-info/entry_points.txt
janus_quantum-1.0.2.dist-info/top_level.txt
janus_quantum-1.0.2.dist-info/RECORD
