Metadata-Version: 2.1
Name: janus-quantum
Version: 1.0.2
Summary: 轻量级量子电路构建、模拟和编译框架
Author-email: Janus Team <janus@example.com>
Maintainer-email: Janus Team <janus@example.com>
License: MIT
Project-URL: Homepage, https://github.com/DebinXiangQuantum/Janus-compiler
Project-URL: Documentation, https://janus-quantum.readthedocs.io
Project-URL: Repository, https://github.com/DebinXiangQuantum/Janus-compiler
Project-URL: Issues, https://github.com/DebinXiangQuantum/Janus-compiler/issues
Project-URL: Changelog, https://github.com/DebinXiangQuantum/Janus-compiler/blob/main/CHANGELOG.md
Keywords: quantum,quantum-computing,quantum-circuit,quantum-simulation,qubits
Classifier: Development Status :: 4 - Beta
Classifier: Intended Audience :: Developers
Classifier: Intended Audience :: Science/Research
Classifier: License :: OSI Approved :: MIT License
Classifier: Operating System :: OS Independent
Classifier: Programming Language :: Python :: 3
Classifier: Programming Language :: Python :: 3.9
Classifier: Programming Language :: Python :: 3.10
Classifier: Programming Language :: Python :: 3.11
Classifier: Programming Language :: Python :: 3.12
Classifier: Programming Language :: Python :: 3.13
Classifier: Topic :: Scientific/Engineering :: Physics
Classifier: Topic :: Software Development :: Libraries :: Python Modules
Requires-Python: >=3.9
License-File: LICENSE
Requires-Dist: numpy>=1.20.0
Requires-Dist: scipy>=1.7.0
Requires-Dist: rustworkx>=0.12.0
Provides-Extra: dev
Requires-Dist: pytest>=7.0.0; extra == "dev"
Requires-Dist: pytest-cov>=4.0.0; extra == "dev"
Requires-Dist: black>=23.0.0; extra == "dev"
Requires-Dist: isort>=5.0.0; extra == "dev"
Requires-Dist: mypy>=1.0.0; extra == "dev"
Provides-Extra: docs
Requires-Dist: sphinx>=7.0.0; extra == "docs"
Requires-Dist: sphinx-book-theme>=1.0.0; extra == "docs"
Requires-Dist: sphinx-copybutton>=0.5.0; extra == "docs"
Requires-Dist: myst-parser>=2.0.0; extra == "docs"
Provides-Extra: full
Requires-Dist: janus-quantum[dev,docs,visualization]; extra == "full"
Provides-Extra: visualization
Requires-Dist: matplotlib>=3.3.0; extra == "visualization"
